djasync/__init__.py
djasync/admin.py
djasync/apps.py
djasync/async_view.py
djasync/await_tag.py
djasync/models.py
djasync/tests.py
myapp/__init__.py
myapp/admin.py
myapp/apps.py
myapp/models.py
myapp/tests.py
myapp/views.py
django_djasync-0.3.1.dist-info/LICENSE
django_djasync-0.3.1.dist-info/METADATA
django_djasync-0.3.1.dist-info/WHEEL
django_djasync-0.3.1.dist-info/top_level.txt
django_djasync-0.3.1.dist-info/RECORD
