Metadata-Version: 2.1
Name: django-djasync
Version: 0.3.1
Summary: A line of description
Home-page: https://github.com/KshitijMhatre/scratchpad/
Author: Kshitij Mhatre
Author-email: kshitijpmhatre@gmail.com
License: MIT
Platform: UNKNOWN
Requires-Dist: Django
